reg/vsrc/seg.v
module seg(
    input [3:0] i_seg,
    output reg [7:0] o_seg
);
    parameter num0 = 8'b1111_1100;
    parameter num1 = 8'b0110_0000;
    parameter num2 = 8'b1101_1010;
    parameter num3 = 8'b1111_0010;
    parameter num4 = 8'b0110_0110;
    parameter num5 = 8'b1011_0110;
    parameter num6 = 8'b1011_1110;
    parameter num7 = 8'b1110_0000;
    parameter num8 = 8'b1111_1110;
    parameter num9 = 8'b1110_0110;
    parameter numa = 8'b1110_1110;
    parameter numb = 8'b0011_1110;
    parameter numc = 8'b1001_1100;
    parameter numd = 8'b0111_1010;
    parameter nume = 8'b1001_1110;
    parameter numf = 8'b1000_1110;
    
    always @(i_seg) begin
        case(i_seg)
            4'd0 : o_seg = ~num0;
            4'd1 : o_seg = ~num1;
            4'd2 : o_seg = ~num2;
            4'd3 : o_seg = ~num3;
            4'd4 : o_seg = ~num4;
            4'd5 : o_seg = ~num5;
            4'd6 : o_seg = ~num6;
            4'd7 : o_seg = ~num7;
            4'd8 : o_seg = ~num8;
            4'd9 : o_seg = ~num9;
            4'd10: o_seg = ~numa;
            4'd11: o_seg = ~numb;
            4'd12: o_seg = ~numc;
            4'd13: o_seg = ~numd;
            4'd14: o_seg = ~nume;
            4'd15: o_seg = ~numf;
        endcase
    end
endmodule

reg/vsrc/seg_hex.v
module seg_hex(
    input [7:0] i_seg,
    output [7:0] o_seg_0,o_seg_1
);

    seg u0_seg(.i_seg(i_seg[3:0]), .o_seg(o_seg_0));
    seg u1_seg(.i_seg(i_seg[7:4]), .o_seg(o_seg_1));
endmodule

reg/vsrc/d_reg.v
module d_reg(
    input clk,
    input i_d,
    output reg o_q
);

    always @(posedge clk) begin
        o_q <= i_d;
    end
endmodule

reg/vsrc/lfsr.v
module lfsr(
    input       clk,
    input       rst,
    input [7:0] i_sed,
    input       i_rand_flag,
    output reg [7:0] o_rand 
);
    reg [3:0] count;
    wire [7:0] o_q; 
    wire o_q_0;
    reg o_q_1;
    assign o_q_0 = (count == 4'd8)?o_q[7] ^ o_q[5] ^ o_q[4] ^ o_q[3]:o_q_1;
    d_reg u0(.clk(clk), .i_d(o_q_0), .o_q(o_q[0]));
    d_reg u1(.clk(clk), .i_d(o_q[0]), .o_q(o_q[1]));
    d_reg u2(.clk(clk), .i_d(o_q[1]), .o_q(o_q[2]));
    d_reg u3(.clk(clk), .i_d(o_q[2]), .o_q(o_q[3]));
    d_reg u4(.clk(clk), .i_d(o_q[3]), .o_q(o_q[4]));
    d_reg u5(.clk(clk), .i_d(o_q[4]), .o_q(o_q[5]));
    d_reg u6(.clk(clk), .i_d(o_q[5]), .o_q(o_q[6]));
    d_reg u7(.clk(clk), .i_d(o_q[6]), .o_q(o_q[7]));
    always @(negedge clk or posedge rst) begin
        if(rst) begin
            count <= 4'b0000;
            o_rand <= 8'b0;
            o_q_1 <= 1'b0;
        end
        if(count < 4'd8) begin
            o_q_1 <= i_sed[count[2:0]];
            count <= count + 1'b1;
            o_rand <= 8'b0;
        end
        else if(count == 4'd8) begin
            count <= count;
            o_q_1 <= 1'b0;
            if(i_rand_flag) o_rand <= o_q[7:0];
            else o_rand <= o_rand;
        end
    end
endmodule

reg/vsrc/reg_top.v
module reg_top(
    input clk,
    input rst,
    input [7:0] i_sed,
    input       i_rand_flag,
    output [7:0] o_seg_1,
    output [7:0] o_seg_0,
    output [7:0] o_led,
    output       o_rand_flag
);

    lfsr u0_lfsr(
        .clk(clk), 
        .rst(rst), 
        .i_sed(i_sed), 
        .i_rand_flag(i_rand_flag), 
        .o_rand(o_led)
    );

    seg_hex u0_seg_hex(
        .i_seg(o_led),
        .o_seg_0(o_seg_0),
        .o_seg_1(o_seg_1)
    );

    assign o_rand_flag = i_rand_flag;
endmodule

reg/alu_top.vcd
$version Generated by VerilatedVcd $end
$timescale 1s $end

 $scope module TOP $end
  $var wire  1 , clk $end
  $var wire  1 / i_rand_flag $end
  $var wire  8 . i_sed [7:0] $end
  $var wire  8 2 o_led [7:0] $end
  $var wire  1 3 o_rand_flag $end
  $var wire  8 1 o_seg_0 [7:0] $end
  $var wire  8 0 o_seg_1 [7:0] $end
  $var wire  1 - rst $end
  $scope module reg_top $end
   $var wire  1 , clk $end
   $var wire  1 / i_rand_flag $end
   $var wire  8 . i_sed [7:0] $end
   $var wire  8 2 o_led [7:0] $end
   $var wire  1 3 o_rand_flag $end
   $var wire  8 1 o_seg_0 [7:0] $end
   $var wire  8 0 o_seg_1 [7:0] $end
   $var wire  1 - rst $end
   $scope module u0_lfsr $end
    $var wire  1 , clk $end
    $var wire  4 4 count [3:0] $end
    $var wire  1 / i_rand_flag $end
    $var wire  8 . i_sed [7:0] $end
    $var wire  8 # o_q [7:0] $end
    $var wire  1 5 o_q_0 $end
    $var wire  1 6 o_q_1 $end
    $var wire  8 2 o_rand [7:0] $end
    $var wire  1 - rst $end
    $scope module u0 $end
     $var wire  1 , clk $end
     $var wire  1 5 i_d $end
     $var wire  1 $ o_q $end
    $upscope $end
    $scope module u1 $end
     $var wire  1 , clk $end
     $var wire  1 $ i_d $end
     $var wire  1 % o_q $end
    $upscope $end
    $scope module u2 $end
     $var wire  1 , clk $end
     $var wire  1 % i_d $end
     $var wire  1 & o_q $end
    $upscope $end
    $scope module u3 $end
     $var wire  1 , clk $end
     $var wire  1 & i_d $end
     $var wire  1 ' o_q $end
    $upscope $end
    $scope module u4 $end
     $var wire  1 , clk $end
     $var wire  1 ' i_d $end
     $var wire  1 ( o_q $end
    $upscope $end
    $scope module u5 $end
     $var wire  1 , clk $end
     $var wire  1 ( i_d $end
     $var wire  1 ) o_q $end
    $upscope $end
    $scope module u6 $end
     $var wire  1 , clk $end
     $var wire  1 ) i_d $end
     $var wire  1 * o_q $end
    $upscope $end
    $scope module u7 $end
     $var wire  1 , clk $end
     $var wire  1 * i_d $end
     $var wire  1 + o_q $end
    $upscope $end
   $upscope $end
   $scope module u0_seg_hex $end
    $var wire  8 2 i_seg [7:0] $end
    $var wire  8 1 o_seg_0 [7:0] $end
    $var wire  8 0 o_seg_1 [7:0] $end
    $scope module u0_seg $end
     $var wire  4 7 i_seg [3:0] $end
     $var wire  8 9 num0 [7:0] $end
     $var wire  8 : num1 [7:0] $end
     $var wire  8 ; num2 [7:0] $end
     $var wire  8 < num3 [7:0] $end
     $var wire  8 = num4 [7:0] $end
     $var wire  8 > num5 [7:0] $end
     $var wire  8 ? num6 [7:0] $end
     $var wire  8 @ num7 [7:0] $end
     $var wire  8 A num8 [7:0] $end
     $var wire  8 B num9 [7:0] $end
     $var wire  8 C numa [7:0] $end
     $var wire  8 D numb [7:0] $end
     $var wire  8 E numc [7:0] $end
     $var wire  8 F numd [7:0] $end
     $var wire  8 G nume [7:0] $end
     $var wire  8 H numf [7:0] $end
     $var wire  8 1 o_seg [7:0] $end
    $upscope $end
    $scope module u1_seg $end
     $var wire  4 8 i_seg [3:0] $end
     $var wire  8 9 num0 [7:0] $end
     $var wire  8 : num1 [7:0] $end
     $var wire  8 ; num2 [7:0] $end
     $var wire  8 < num3 [7:0] $end
     $var wire  8 = num4 [7:0] $end
     $var wire  8 > num5 [7:0] $end
     $var wire  8 ? num6 [7:0] $end
     $var wire  8 @ num7 [7:0] $end
     $var wire  8 A num8 [7:0] $end
     $var wire  8 B num9 [7:0] $end
     $var wire  8 C numa [7:0] $end
     $var wire  8 D numb [7:0] $end
     $var wire  8 E numc [7:0] $end
     $var wire  8 F numd [7:0] $end
     $var wire  8 G nume [7:0] $end
     $var wire  8 H numf [7:0] $end
     $var wire  8 0 o_seg [7:0] $end
    $upscope $end
   $upscope $end
  $upscope $end
 $upscope $end
$enddefinitions $end


#1
b00000000 #
0$
0%
0&
0'
0(
0)
0*
0+
1,
1-
b10011001 .
0/
b00000011 0
b00000011 1
b00000000 2
03
b0000 4
05
06
b0000 7
b0000 8
b11111100 9
b01100000 :
b11011010 ;
b11110010 <
b01100110 =
b10110110 >
b10111110 ?
b11100000 @
b11111110 A
b11100110 B
b11101110 C
b00111110 D
b10011100 E
b01111010 F
b10011110 G
b10001110 H
#2
0,
#3
1,
b0001 4
15
16
#4
b00000001 #
1$
0,
#5
1,
b0010 4
05
06
#6
b00000010 #
0$
1%
0,
#7
1,
b0011 4
#8
b00000100 #
0%
1&
0,
#9
1,
b0100 4
15
16
#10
b00001001 #
1$
0&
1'
0,
#11
1,
b0101 4
#12
b00010011 #
1%
0'
1(
0,
#13
1,
b0110 4
05
06
#14
b00100110 #
0$
1&
0(
1)
0,
#15
1,
b0111 4
#16
b01001100 #
0%
1'
0)
1*
0,
1/
13
#17
1,
b1000 4
15
16
#18
b10011001 #
1$
0&
1(
0*
1+
0,
#19
1,
b00011001 0
b00011001 1
b10011001 2
06
b1001 7
b1001 8
#20
b00110011 #
1%
0'
1)
0+
0,
05
#21
1,
b00001101 0
b00001101 1
b00110011 2
b0011 7
b0011 8
#22
b01100110 #
0$
1&
0(
1*
0,
15
#23
1,
b01000001 0
b01000001 1
b01100110 2
b0110 7
b0110 8
#24
b11001101 #
1$
0%
1'
0)
1+
0,
05
#25
1,
b01100011 0
b10000101 1
b11001101 2
b1101 7
b1100 8
#26
b10011010 #
0$
1%
0&
1(
0*
0,
15
#27
1,
b00011001 0
b00010001 1
b10011010 2
b1010 7
b1001 8
#28
b00110101 #
1$
0%
1&
0'
1)
0+
0,
05
#29
1,
b00001101 0
b01001001 1
b00110101 2
b0101 7
b0011 8
#30
b01101010 #
0$
1%
0&
1'
0(
1*
0,
#31
1,
b01000001 0
b00010001 1
b01101010 2
b1010 7
b0110 8
#32
b11010100 #
0%
1&
0'
1(
0)
1+
0,
#33
1,
b10000101 0
b10011001 1
b11010100 2
b0100 7
b1101 8
#34
b10101000 #
0&
1'
0(
1)
0*
0,
15
#35
1,
b00010001 0
b00000001 1
b10101000 2
b1000 7
b1010 8
#36
b01010001 #
1$
0'
1(
0)
1*
0+
0,
0/
03
#37
1,
#38
b10100011 #
1%
0(
1)
0*
1+
0,
05
#39
1,
#40
b01000110 #
0$
1&
0)
1*
0+
0,
#41
1,
#42
b10001100 #
0%
1'
0*
1+
0,
#43
1,
#44
b00011000 #
0&
1(
0+
0,
#45
1,
#46
b00110000 #
0'
1)
0,
