FSM/vsrc/fsm.v
module fsm(
    input clk,in,reset,
    output out
);

    parameter [2:0] S0 = 0, S1 = 1, S2 = 2, S3 = 3, S4 = 4;
    reg [2:0] state_din, state_dout;
    reg in_d1,in_d2;
    wire in_flag_p,in_flag_n,in_flag;

    assign in_flag_p = (in == in_d1)?1'b1:1'b0;
    assign in_flag_n = (in == in_d2)?1'b1:1'b0;
    assign in_flag = in_flag_p & in_flag_n;

    always @(posedge clk or negedge reset) begin
        if(!reset) in_d1 <= 1'b0;
        else in_d1 <= in;
    end

    always @(negedge clk,reset) begin
        if(!reset) in_d2 <= 1'b0;
        else in_d2 <= in;
    end
    
    always @(negedge clk,reset) begin
        if(!reset)
            state_din <= S0;
        else
            state_din <= state_dout;
    end

    always @(posedge clk or negedge reset) begin
        case(state_din)
            S0: begin
                if(in_flag) state_dout <= S1;
                else state_dout <= S0;
            end
            S1: begin
                if(in_flag) state_dout <= S2;
                else state_dout <= S0;
            end
            S2: begin
                if(in_flag) state_dout <= S3;
                else state_dout <= S0;
            end
            S3: begin
                if(in_flag) state_dout <= S4;
                else state_dout <= S0;
            end
            S4: begin
                if(in_flag) state_dout <= S4;
                else state_dout <= S0;
            end
            default: state_dout <= S0;
        endcase
    end

    assign out = (state_dout == S4)?1'b1:1'b0;
endmodule

FSM/fsm.vcd
$version Generated by VerilatedVcd $end
$timescale 1s $end

 $scope module TOP $end
  $var wire  1 # clk $end
  $var wire  1 $ in $end
  $var wire  1 & out $end
  $var wire  1 % reset $end
  $scope module fsm $end
   $var wire  3 . S0 [2:0] $end
   $var wire  3 / S1 [2:0] $end
   $var wire  3 0 S2 [2:0] $end
   $var wire  3 1 S3 [2:0] $end
   $var wire  3 2 S4 [2:0] $end
   $var wire  1 # clk $end
   $var wire  1 $ in $end
   $var wire  1 ) in_d1 $end
   $var wire  1 * in_d2 $end
   $var wire  1 - in_flag $end
   $var wire  1 , in_flag_n $end
   $var wire  1 + in_flag_p $end
   $var wire  1 & out $end
   $var wire  1 % reset $end
   $var wire  3 ' state_din [2:0] $end
   $var wire  3 ( state_dout [2:0] $end
  $upscope $end
 $upscope $end
$enddefinitions $end


#1
0#
0$
0%
0&
b000 '
b000 (
0)
0*
1+
1,
1-
b000 .
b001 /
b010 0
b011 1
b100 2
#2
1#
b001 (
#3
0#
#4
1#
#5
0#
#6
1#
1%
b001 '
#7
0#
1$
1*
0+
0-
#8
1#
0$
b000 (
1+
0,
#9
0#
1$
b000 '
0+
1,
#10
1#
1)
1+
1-
#11
0#
#12
1#
b001 (
#13
0#
0$
b001 '
0*
0+
0-
#14
1#
b000 (
0)
1+
1-
#15
0#
1$
b000 '
1*
0+
0-
#16
1#
1)
1+
1-
#17
0#
0$
0*
0+
0-
#18
1#
1$
1+
0,
#19
0#
0$
0+
1,
#20
1#
1$
1+
0,
#21
0#
1*
1,
1-
#22
1#
0$
0)
0,
0-
#23
0#
0*
1,
1-
#24
1#
b001 (
#25
0#
b001 '
#26
1#
b010 (
#27
0#
1$
b010 '
1*
0+
0-
#28
1#
0$
b000 (
1+
0,
#29
0#
1$
b000 '
0+
1,
#30
1#
1)
1+
1-
#31
0#
0$
0*
0+
0-
#32
1#
0)
1+
1-
#33
0#
#34
1#
1$
1)
0,
0-
#35
0#
1*
1,
1-
#36
1#
b001 (
#37
0#
b001 '
#38
1#
0$
b000 (
0)
0,
0-
#39
0#
b000 '
0*
1,
1-
#40
1#
b001 (
#41
0#
1$
b001 '
1*
0+
0-
#42
1#
b000 (
1)
1+
1-
#43
0#
b000 '
#44
1#
0$
0)
0,
0-
#45
0#
1$
0+
1,
#46
1#
0$
1+
0,
#47
0#
1$
0+
1,
#48
1#
1)
1+
1-
#49
0#
#50
1#
b001 (
#51
0#
0$
b001 '
0*
0+
0-
#52
1#
1$
b000 (
1+
0,
#53
0#
0$
b000 '
0+
1,
#54
1#
0)
1+
1-
#55
0#
1$
1*
0+
0-
#56
1#
0$
1+
0,
#57
0#
1$
0+
1,
#58
1#
0$
1+
0,
#59
0#
1$
0+
1,
#60
1#
0$
1+
0,
#61
0#
0*
1,
1-
#62
1#
1$
1)
0,
0-
#63
0#
0$
0+
1,
#64
1#
0)
1+
1-
#65
0#
#66
1#
1$
1)
0,
0-
#67
0#
1*
1,
1-
#68
1#
b001 (
#69
0#
0$
b001 '
0*
0+
0-
#70
1#
1$
b000 (
1+
0,
#71
0#
0$
b000 '
0+
1,
#72
1#
1$
1+
0,
#73
0#
0$
0+
1,
#74
1#
1$
1+
0,
#75
0#
1*
1,
1-
#76
1#
b001 (
#77
0#
0$
b001 '
0*
0+
0-
#78
1#
1$
b000 (
1+
0,
#79
0#
0$
b000 '
0+
1,
#80
1#
1$
1+
0,
#81
0#
0$
0+
1,
#82
1#
1$
1+
0,
#83
0#
0$
0+
1,
#84
1#
0)
1+
1-
#85
0#
1$
1*
0+
0-
#86
1#
0$
1+
0,
#87
0#
1$
0+
1,
#88
1#
0$
1+
0,
#89
0#
0*
1,
1-
#90
1#
b001 (
#91
0#
b001 '
#92
1#
b010 (
#93
0#
1$
b010 '
1*
0+
0-
#94
1#
b000 (
1)
1+
1-
#95
0#
0$
b000 '
0*
0+
0-
#96
1#
1$
1+
0,
#97
0#
0$
0+
1,
#98
1#
0)
1+
1-
#99
0#
#100
1#
b001 (
#101
0#
1$
b001 '
1*
0+
0-
#102
1#
0$
b000 (
1+
0,
#103
0#
b000 '
0*
1,
1-
#104
1#
b001 (
#105
0#
b001 '
#106
1#
1$
b000 (
1)
0,
0-
#107
0#
b000 '
1*
1,
1-
#108
1#
0$
0)
0,
0-
#109
0#
0*
1,
1-
#110
1#
b001 (
#111
0#
1$
b001 '
1*
0+
0-
#112
1#
b000 (
1)
1+
1-
#113
0#
b000 '
#114
1#
0$
0)
0,
0-
#115
0#
1$
0+
1,
#116
1#
0$
1+
0,
#117
0#
0*
1,
1-
#118
1#
b001 (
#119
0#
1$
b001 '
1*
0+
0-
#120
1#
0$
b000 (
1+
0,
#121
0#
b000 '
0*
1,
1-
#122
1#
1$
1)
0,
0-
#123
0#
1*
1,
1-
#124
1#
b001 (
#125
0#
0$
b001 '
0*
0+
0-
#126
1#
1$
b000 (
1+
0,
#127
0#
0$
b000 '
0+
1,
#128
1#
1$
1+
0,
#129
0#
1*
1,
1-
#130
1#
b001 (
#131
0#
b001 '
#132
1#
b010 (
#133
0#
b010 '
#134
1#
b011 (
#135
0#
b011 '
#136
1#
1&
b100 (
#137
0#
b100 '
#138
1#
0$
0&
b000 (
0)
0,
0-
#139
0#
1$
b000 '
0+
1,
#140
1#
1)
1+
1-
#141
0#
0$
0*
0+
0-
#142
1#
1$
1+
0,
#143
0#
0$
0+
1,
#144
1#
1$
1+
0,
#145
0#
1*
1,
1-
#146
1#
0$
0)
0,
0-
#147
0#
0*
1,
1-
#148
1#
1$
1)
0,
0-
#149
0#
0$
0+
1,
#150
1#
1$
1+
0,
#151
0#
1*
1,
1-
#152
1#
b001 (
#153
0#
0$
b001 '
0*
0+
0-
#154
1#
b000 (
0)
1+
1-
#155
0#
b000 '
#156
1#
1$
1)
0,
0-
#157
0#
0$
0+
1,
#158
1#
1$
1+
0,
#159
0#
0$
0+
1,
#160
1#
1$
1+
0,
#161
0#
0$
0+
1,
#162
1#
1$
1+
0,
#163
0#
0$
0+
1,
#164
1#
1$
1+
0,
#165
0#
1*
1,
1-
#166
1#
b001 (
#167
0#
b001 '
#168
1#
0$
b000 (
0)
0,
0-
#169
0#
b000 '
0*
1,
1-
#170
1#
b001 (
#171
0#
1$
b001 '
1*
0+
0-
#172
1#
0$
b000 (
1+
0,
#173
0#
1$
b000 '
0+
1,
#174
1#
0$
1+
0,
#175
0#
0*
1,
1-
#176
1#
b001 (
#177
0#
b001 '
#178
1#
b010 (
#179
0#
1$
b010 '
1*
0+
0-
#180
1#
0$
b000 (
1+
0,
#181
0#
1$
b000 '
0+
1,
#182
1#
1)
1+
1-
#183
0#
#184
1#
b001 (
#185
0#
b001 '
#186
1#
0$
b000 (
0)
0,
0-
#187
0#
b000 '
0*
1,
1-
#188
1#
1$
1)
0,
0-
#189
0#
1*
1,
1-
#190
1#
0$
0)
0,
0-
#191
0#
1$
0+
1,
#192
1#
1)
1+
1-
#193
0#
0$
0*
0+
0-
#194
1#
1$
1+
0,
#195
0#
0$
0+
1,
#196
1#
1$
1+
0,
#197
0#
1*
1,
1-
#198
1#
b001 (
#199
0#
b001 '
#200
1#
b010 (
#201
0#
0$
b010 '
0*
0+
0-
